LICENSE
README.md
xcat/__init__.py
xcat/algorithms.py
xcat/attack.py
xcat/cli.py
xcat/display.py
xcat/features.py
xcat/injections.py
xcat/oob.py
xcat/shell.py
xcat/utils.py
xcat-1.1.0.dist-info/entry_points.txt
xcat-1.1.0.dist-info/LICENSE
xcat-1.1.0.dist-info/WHEEL
xcat-1.1.0.dist-info/METADATA
xcat-1.1.0.dist-info/RECORD
