Metadata-Version: 2.1
Name: xcat
Version: 1.1.0
Summary: A command line tool to automate the exploitation of blind XPath injection vulnerabilities
Home-page: https://github.com/orf/xcat
License: MIT
Author: Tom Forbes
Author-email: tom@tomforb.es
Requires-Python: >=3.7
Classifier: License :: OSI Approved :: MIT License
Classifier: Programming Language :: Python :: 3
Classifier: Programming Language :: Python :: 3.7
Classifier: Programming Language :: Python :: 3.8
Requires-Dist: aiodns
Requires-Dist: aiohttp (>=3.0.0,<4.0.0)
Requires-Dist: appdirs
Requires-Dist: cchardet
Requires-Dist: click
Requires-Dist: colorama
Requires-Dist: prompt-toolkit (<4)
Requires-Dist: xpath-expressions (>=1.0.0,<2.0.0)
